{"created_at":"Thu Feb 20 00:50:56 +0000 2014","id":436301910337781760,"id_str":"436301910337781760","text":"#NowPlaying \"Dream On\" by Aerosmith","source":"web","truncated":false,"in_reply_to_status_id":null,"in_reply_to_status_id_str":null,"in_reply_to_user_id":null,"in_reply_to_user_id_str":null,"in_reply_to_screen_name":null,"user":{"id":436429045,"id_str":"436429045","name":"gabe cohen","screen_name":"cool_hWhip_","location":"Comedy Cries","url":"https:\/\/twitter.com\/ComedyCries","description":"Aspiring author (CELL, MAFIOSO, DOG'S DIARY, PRISTINE), comicbook writer (POWERHOUSE MOVEMENT, JANEIRO'S ROYAL HELL, QUAD-FORCE), & screenwriter (PHANTOM SQUAD)","protected":false,"followers_count":430,"friends_count":33,"listed_count":1,"created_at":"Wed Dec 14 05:15:56 +0000 2011","favourites_count":97,"utc_offset":-28800,"time_zone":"Pacific Time (US & Canada)","geo_enabled":false,"verified":false,"statuses_count":40536,"lang":"en","contributors_enabled":false,"is_translator":false,"is_translation_enabled":false,"profile_background_color":"F0950C","profile_background_image_url":"http:\/\/abs.twimg.com\/images\/themes\/theme2\/bg.gif","profile_background_image_url_https":"https:\/\/abs.twimg.com\/images\/themes\/theme2\/bg.gif","profile_background_tile":false,"profile_image_url":"http:\/\/pbs.twimg.com\/profile_images\/417544772975218688\/xKBVlNvk_normal.jpeg","profile_image_url_https":"https:\/\/pbs.twimg.com\/profile_images\/417544772975218688\/xKBVlNvk_normal.jpeg","profile_banner_url":"https:\/\/pbs.twimg.com\/profile_banners\/436429045\/1390005660","profile_link_color":"EB1212","profile_sidebar_border_color":"000000","profile_sidebar_fill_color":"DDEEF6","profile_text_color":"333333","profile_use_background_image":true,"default_profile":false,"default_profile_image":false,"following":null,"follow_request_sent":null,"notifications":null},"geo":null,"coordinates":null,"place":null,"contributors":null,"retweet_count":0,"favorite_count":0,"entities":{"hashtags":[{"text":"NowPlaying","indices":[0,11]}],"symbols":[],"urls":[],"user_mentions":[]},"favorited":false,"retweeted":false,"filter_level":"medium","lang":"et"}
